akeneo_cli/__init__.py
akeneo_cli/client.py
akeneo_cli/exceptions.py
akeneo_cli/main.py
akeneo_cli-1.0.9.dist-info/LICENSE
akeneo_cli-1.0.9.dist-info/METADATA
akeneo_cli-1.0.9.dist-info/WHEEL
akeneo_cli-1.0.9.dist-info/entry_points.txt
akeneo_cli-1.0.9.dist-info/top_level.txt
akeneo_cli-1.0.9.dist-info/RECORD
