Metadata-Version: 2.1
Name: akeneo-cli
Version: 1.0.9
Summary: CLI for Akeneo API
Home-page: https://github.com/tms-software/akeneo-cli
Author: Franck COUTOULY
Author-email: franck.coutouly@tms-software.ch
Classifier: Programming Language :: Python :: 3
Classifier: License :: OSI Approved :: MIT License
Classifier: Operating System :: OS Independent
Requires-Python: >=3.6, <4
License-File: LICENSE
Requires-Dist: requests
Requires-Dist: python-magic
